yalla/__init__.py
yalla/avanti.py
yalla/calcul.py
yalla/config.py
yalla/env.py
yalla/fichiers.py
yalla/info.py
yalla/job.py
yalla/launcher.py
yalla/logserver.py
yalla/messages.py
yalla/testSweep.py
yalla-0.6.1.data/data/AUTHORS
yalla-0.6.1.data/data/LICENSE.txt
yalla-0.6.1.data/data/tests/a.f90
yalla-0.6.1.data/data/tests/a_mpi.f
yalla-0.6.1.data/data/tests/run_one_proc_with_debug.sh
yalla-0.6.1.data/data/tests/run_with_debug.sh
yalla-0.6.1.data/data/tests/testSweep.py
yalla-0.6.1.data/data/tests/testexe.py
yalla-0.6.1.data/data/yalla/avanti/Makefile.neserpp
yalla-0.6.1.data/data/yalla/avanti/Makefile.shaheen
yalla-0.6.1.data/data/yalla/avanti/Makefile.stampede
yalla-0.6.1.data/data/yalla/avanti/Makefile.stampedepp
yalla-0.6.1.data/data/yalla/avanti/avanti.c
yalla-0.6.1.data/data/yalla/avanti/avantipp.c
yalla-0.6.1.data/data/yalla/avanti/job.localhost
yalla-0.6.1.data/data/yalla/avanti/job.neserpp
yalla-0.6.1.data/data/yalla/avanti/job.shaheen
yalla-0.6.1.data/data/yalla/avanti/job.stampede
yalla-0.6.1.data/data/yalla/avanti/job.stampedepp
yalla-0.6.1.data/data/yalla/pp/README
yalla-0.6.1.data/data/yalla/pp/avanti.py
yalla-0.6.1.data/data/yalla/pp/avanti.sub
yalla-0.6.1.data/data/yalla/pp/avanti_callback.py
yalla-0.6.1.data/data/yalla/pp/avanti_callback.sub
yalla-0.6.1.data/data/yalla/pp/client.py
yalla-0.6.1.data/data/yalla/pp/job.sub
yalla-0.6.1.data/data/yalla/pp/pp.py
yalla-0.6.1.data/data/yalla/pp/ppauto.py
yalla-0.6.1.data/data/yalla/pp/ppserver.py
yalla-0.6.1.data/data/yalla/pp/pptransport.py
yalla-0.6.1.data/data/yalla/pp/ppworker.py
yalla-0.6.1.dist-info/DESCRIPTION.rst
yalla-0.6.1.dist-info/METADATA
yalla-0.6.1.dist-info/RECORD
yalla-0.6.1.dist-info/WHEEL
yalla-0.6.1.dist-info/metadata.json
yalla-0.6.1.dist-info/top_level.txt
